xfem/utils.py
xfem/__init__.py
xfem/ngs_check.py
xfem/lsetcurv.py
xfem/ngsxfem_py.so
xfem/cutmg.py
xfem/lset_spacetime.py
xfem/mlset.py
xfem_avx2.libs/libngfem-8914e8a2.so
xfem_avx2.libs/libngbla-ac1e7255.so
xfem_avx2.libs/libngla-264430c8.so
xfem_avx2.libs/libngcomp-33810221.so
xfem_avx2.libs/libsolve-62f57152.so
xfem_avx2.libs/libngstd-2c94147d.so
xfem_avx2-2.0.2204.dist-info/top_level.txt
xfem_avx2-2.0.2204.dist-info/LICENSE
xfem_avx2-2.0.2204.dist-info/METADATA
xfem_avx2-2.0.2204.dist-info/RECORD
xfem_avx2-2.0.2204.dist-info/WHEEL
