Metadata-Version: 2.1
Name: xfem-avx2
Version: 2.0.2204
Summary: (ngs)xfem is an Add-on library to Netgen/NGSolve for unfitted/cut FEM.
Home-page: https://github.com/ngsxfem/ngsxfem
Author: Christoph Lehrenfeld
Author-email: lehrenfeld@math.uni-goettingen.de
Requires-Python: >=3.8
License-File: LICENSE
